nanobench/__init__.py
nanobench-0.1.0.dist-info/METADATA
nanobench-0.1.0.dist-info/WHEEL
nanobench-0.1.0.dist-info/entry_points.txt
nanobench-0.1.0.dist-info/top_level.txt
nanobench-0.1.0.dist-info/RECORD
