Metadata-Version: 2.4
Name: nanobench
Version: 0.1.0
Summary: Eval framework
Author-email: Mathias Lechner <mathias@liquid.ai>
License: MIT
Project-URL: Homepage, https://github.com/yourusername/nanobench
Project-URL: Repository, https://github.com/yourusername/nanobench
Classifier: Development Status :: 3 - Alpha
Classifier: Intended Audience :: Developers
Classifier: License :: OSI Approved :: MIT License
Classifier: Programming Language :: Python :: 3
Classifier: Programming Language :: Python :: 3.7
Classifier: Programming Language :: Python :: 3.8
Classifier: Programming Language :: Python :: 3.9
Classifier: Programming Language :: Python :: 3.10
Classifier: Programming Language :: Python :: 3.11
Classifier: Programming Language :: Python :: 3.12
Requires-Python: >=3.7
